openslide/__init__.py
openslide/_convert.pyd
openslide/_convert.pyi
openslide/_version.py
openslide/deepzoom.py
openslide/lowlevel.py
openslide/py.typed
openslide_python-1.4.3.dist-info/licenses/COPYING.LESSER
openslide_python-1.4.3.dist-info/licenses/examples/deepzoom/licenses/LICENSE.jquery
openslide_python-1.4.3.dist-info/licenses/examples/deepzoom/licenses/LICENSE.openseadragon
openslide_python-1.4.3.dist-info/licenses/examples/deepzoom/licenses/LICENSE.openseadragon-scalebar
openslide_python-1.4.3.dist-info/METADATA
openslide_python-1.4.3.dist-info/WHEEL
openslide_python-1.4.3.dist-info/top_level.txt
openslide_python-1.4.3.dist-info/RECORD
