Metadata-Version: 2.4
Name: openslide-python
Version: 1.4.3
Summary: Python interface to OpenSlide
Maintainer-email: OpenSlide project <openslide-users@lists.andrew.cmu.edu>
License-Expression: LGPL-2.1-only AND BSD-3-Clause AND MIT AND LicenseRef-Public-Domain
Project-URL: Homepage, https://openslide.org/
Project-URL: Documentation, https://openslide.org/api/python/
Project-URL: Release notes, https://github.com/openslide/openslide-python/blob/main/CHANGELOG.md
Project-URL: Repository, https://github.com/openslide/openslide-python
Keywords: OpenSlide,whole-slide image,virtual slide,library
Classifier: Development Status :: 5 - Production/Stable
Classifier: Intended Audience :: Developers
Classifier: Intended Audience :: Healthcare Industry
Classifier: Intended Audience :: Science/Research
Classifier: Operating System :: MacOS :: MacOS X
Classifier: Operating System :: Microsoft :: Windows
Classifier: Operating System :: POSIX :: Linux
Classifier: Programming Language :: Python
Classifier: Programming Language :: Python :: 3
Classifier: Programming Language :: Python :: 3.10
Classifier: Programming Language :: Python :: 3.11
Classifier: Programming Language :: Python :: 3.12
Classifier: Programming Language :: Python :: 3.13
Classifier: Programming Language :: Python :: 3.14
Classifier: Programming Language :: Python :: Free Threading :: 2 - Beta
Classifier: Topic :: Scientific/Engineering :: Bio-Informatics
Classifier: Typing :: Typed
Requires-Python: >=3.10
License-File: COPYING.LESSER
License-File: examples/deepzoom/licenses/LICENSE.jquery
License-File: examples/deepzoom/licenses/LICENSE.openseadragon
License-File: examples/deepzoom/licenses/LICENSE.openseadragon-scalebar
Requires-Dist: Pillow
Dynamic: license-file
